don_cv/__init__.py
don_cv/cli.py
don_cv-0.6.0.dist-info/METADATA
don_cv-0.6.0.dist-info/WHEEL
don_cv-0.6.0.dist-info/entry_points.txt
don_cv-0.6.0.dist-info/top_level.txt
don_cv-0.6.0.dist-info/RECORD
