Metadata-Version: 2.1
Name: don-cv
Version: 0.6.0
Summary: A terminal GUI displaying a configurable resume
Home-page: https://github.com/copyleftdev/don
Author: Don Johnson
Author-email: dj@codetestcode.io
Classifier: Programming Language :: Python :: 3
Classifier: License :: OSI Approved :: MIT License
Classifier: Operating System :: OS Independent
Requires-Python: >=3.6
Requires-Dist: rich
Requires-Dist: PyYAML
